torch_cuda_installer/__init__.py
torch_cuda_installer/installer.py
torch_cuda_installer-0.1.0.dist-info/METADATA
torch_cuda_installer-0.1.0.dist-info/WHEEL
torch_cuda_installer-0.1.0.dist-info/entry_points.txt
torch_cuda_installer-0.1.0.dist-info/top_level.txt
torch_cuda_installer-0.1.0.dist-info/RECORD
