Metadata-Version: 2.1
Name: torch-cuda-installer
Version: 0.1.0
Summary: A tool to automatically install PyTorch packages with CUDA support if available
Author-email: Güvenç Usanmaz <gusanmaz@gmail.com>
Project-URL: Homepage, https://github.com/gusanmaz/torch-cuda-installer
Keywords: pytorch,torch,cuda,installer,deep-learning,nvidia
Classifier: License :: OSI Approved :: MIT License
Classifier: Programming Language :: Python
Classifier: Programming Language :: Python :: 3
Requires-Python: >=3.6
Requires-Dist: requests
Provides-Extra: dev
Requires-Dist: pytest; extra == "dev"
